{
    "sourceFile": "src/admin/pages/CMS.jsx",
    "activeCommit": 0,
    "commits": [
        {
            "activePatchIndex": 1,
            "patches": [
                {
                    "date": 1751537658122,
                    "content": "Index: \n===================================================================\n--- \n+++ \n"
                },
                {
                    "date": 1751544725482,
                    "content": "Index: \n===================================================================\n--- \n+++ \n@@ -7,39 +7,68 @@\n   const token = localStorage.getItem(\"token\");\r\n \r\n   useEffect(() => {\r\n     fetch(`${import.meta.env.VITE_AUTH_API_URL}/admin/cms`, {\r\n-      headers: { Authorization: `Bearer ${token}` }\r\n+      headers: { Authorization: `Bearer ${token}` },\r\n     })\r\n-      .then(res => res.json())\r\n-      .then(data => {\r\n+      .then((res) => res.json())\r\n+      .then((data) => {\r\n         setPrivacy(data.privacy || \"\");\r\n         setTerms(data.terms || \"\");\r\n       });\r\n   }, []);\r\n \r\n   const handleSave = async () => {\r\n     await fetch(`${import.meta.env.VITE_AUTH_API_URL}/admin/cms`, {\r\n       method: \"PUT\",\r\n-      headers: { Authorization: `Bearer ${token}`, \"Content-Type\": \"application/json\" },\r\n+      headers: {\r\n+        Authorization: `Bearer ${token}`,\r\n+        \"Content-Type\": \"application/json\",\r\n+      },\r\n       body: JSON.stringify({ privacy, terms }),\r\n     });\r\n     alert(\"Content updated!\");\r\n   };\r\n \r\n   return (\r\n     <AdminLayout>\r\n-      <h1 className=\"text-2xl font-bold mb-4\">CMS</h1>\r\n-      <div className=\"mb-4\">\r\n-        <h2 className=\"font-semibold mb-2\">Privacy Policy</h2>\r\n-        <textarea className=\"w-full border p-2 mb-4\" rows={8} value={privacy} onChange={e => setPrivacy(e.target.value)} />\r\n+      <div className=\"bg-gradient-to-br from-purple-100 to-purple-200 rounded-xl p-6 mb-8 shadow-inner\">\r\n+        <h1 className=\"text-3xl font-extrabold text-purple-800\">CMS Management</h1>\r\n       </div>\r\n-      <div className=\"mb-4\">\r\n\\ No newline at end of file\n-        <h2 className=\"font-semibold mb-2\">Terms & Conditions</h2>\r\n-        <textarea className=\"w-full border p-2 mb-4\" rows={8} value={terms} onChange={e => setTerms(e.target.value)} />\r\n+\r\n+      <div className=\"space-y-8\">\r\n+        <div>\r\n+          <h2 className=\"font-bold mb-2 text-lg text-gray-700\">Privacy Policy</h2>\r\n+          <textarea\r\n+            className=\"w-full border p-3 rounded-lg focus:outline-none focus:ring-2 focus:ring-purple-400\"\r\n+            rows={8}\r\n+            value={privacy}\r\n+            onChange={(e) => setPrivacy(e.target.value)}\r\n+            placeholder=\"Write your Privacy Policy here...\"\r\n+          />\r\n+        </div>\r\n+\r\n+        <div>\r\n+          <h2 className=\"font-bold mb-2 text-lg text-gray-700\">Terms & Conditions</h2>\r\n+          <textarea\r\n+            className=\"w-full border p-3 rounded-lg focus:outline-none focus:ring-2 focus:ring-purple-400\"\r\n+            rows={8}\r\n+            value={terms}\r\n+            onChange={(e) => setTerms(e.target.value)}\r\n+            placeholder=\"Write your Terms & Conditions here...\"\r\n+          />\r\n+        </div>\r\n+\r\n+        <div className=\"flex justify-end\">\r\n+          <button\r\n+            className=\"bg-purple-500 hover:bg-purple-600 text-white px-6 py-2 rounded-lg transition shadow-md\"\r\n+            onClick={handleSave}\r\n+          >\r\n+            Save Changes\r\n+          </button>\r\n+        </div>\r\n       </div>\r\n-      <button className=\"bg-blue-500 text-white px-4 py-2 rounded\" onClick={handleSave}>Save</button>\r\n     </AdminLayout>\r\n   );\r\n };\r\n \r\n-export default CMS;\n+export default CMS;\r\n"
                }
            ],
            "date": 1751537658122,
            "name": "Commit-0",
            "content": "import React, { useEffect, useState } from \"react\";\r\nimport AdminLayout from \"../components/AdminLayout\";\r\n\r\nconst CMS = () => {\r\n  const [privacy, setPrivacy] = useState(\"\");\r\n  const [terms, setTerms] = useState(\"\");\r\n  const token = localStorage.getItem(\"token\");\r\n\r\n  useEffect(() => {\r\n    fetch(`${import.meta.env.VITE_AUTH_API_URL}/admin/cms`, {\r\n      headers: { Authorization: `Bearer ${token}` }\r\n    })\r\n      .then(res => res.json())\r\n      .then(data => {\r\n        setPrivacy(data.privacy || \"\");\r\n        setTerms(data.terms || \"\");\r\n      });\r\n  }, []);\r\n\r\n  const handleSave = async () => {\r\n    await fetch(`${import.meta.env.VITE_AUTH_API_URL}/admin/cms`, {\r\n      method: \"PUT\",\r\n      headers: { Authorization: `Bearer ${token}`, \"Content-Type\": \"application/json\" },\r\n      body: JSON.stringify({ privacy, terms }),\r\n    });\r\n    alert(\"Content updated!\");\r\n  };\r\n\r\n  return (\r\n    <AdminLayout>\r\n      <h1 className=\"text-2xl font-bold mb-4\">CMS</h1>\r\n      <div className=\"mb-4\">\r\n        <h2 className=\"font-semibold mb-2\">Privacy Policy</h2>\r\n        <textarea className=\"w-full border p-2 mb-4\" rows={8} value={privacy} onChange={e => setPrivacy(e.target.value)} />\r\n      </div>\r\n      <div className=\"mb-4\">\r\n        <h2 className=\"font-semibold mb-2\">Terms & Conditions</h2>\r\n        <textarea className=\"w-full border p-2 mb-4\" rows={8} value={terms} onChange={e => setTerms(e.target.value)} />\r\n      </div>\r\n      <button className=\"bg-blue-500 text-white px-4 py-2 rounded\" onClick={handleSave}>Save</button>\r\n    </AdminLayout>\r\n  );\r\n};\r\n\r\nexport default CMS;"
        }
    ]
}